moex/__init__.py
moex/moex_wrapper.py
moex_wrapper-0.1.0.dist-info/licenses/LICENSE
moex_wrapper-0.1.0.dist-info/METADATA
moex_wrapper-0.1.0.dist-info/WHEEL
moex_wrapper-0.1.0.dist-info/top_level.txt
moex_wrapper-0.1.0.dist-info/RECORD
